waduh/__init__.py
waduh/math.py
waduh/utils.py
waduh-0.2.0.dist-info/METADATA
waduh-0.2.0.dist-info/WHEEL
waduh-0.2.0.dist-info/top_level.txt
waduh-0.2.0.dist-info/RECORD
